{
  "_class": "shapePath",
  "booleanOperation": -1,
  "clippingMaskMode": 0,
  "do_objectID": "CE522171-AA38-414C-8B94-3283CE0C956D",
  "edited": true,
  "exportOptions": {
    "_class": "exportOptions",
    "exportFormats": [
    ],
    "includedLayerIds": [
    ],
    "layerOptions": 0,
    "shouldTrim": false
  },
  "frame": {
    "_class": "rect",
    "constrainProportions": false,
    "height": 20.98743538655593,
    "width": 24,
    "x": 0,
    "y": 1.5
  },
  "hasClippingMask": true,
  "isClosed": true,
  "isFixedToViewport": false,
  "isFlippedHorizontal": false,
  "isFlippedVertical": false,
  "isLocked": false,
  "isVisible": true,
  "layerListExpandedType": 0,
  "name": "Mask",
  "nameIsFixed": false,
  "pointRadiusBehaviour": 1,
  "points": [
    {
      "_class": "curvePoint",
      "cornerRadius": 0,
      "curveFrom": "{0, 0}",
      "curveMode": 1,
      "curveTo": "{0, 0}",
      "hasCurveFrom": false,
      "hasCurveTo": false,
      "point": "{0, 0}"
    },
    {
      "_class": "curvePoint",
      "cornerRadius": 0,
      "curveFrom": "{0, 1.0340370471461879}",
      "curveMode": 4,
      "curveTo": "{0, 0.8905838700303752}",
      "hasCurveFrom": true,
      "hasCurveTo": false,
      "point": "{0, 0.8905838700303752}"
    },
    {
      "_class": "curvePoint",
      "cornerRadius": 0,
      "curveFrom": "{0.19642857142857142, 0.8905838700303752}",
      "curveMode": 4,
      "curveTo": "{0.19642857142857142, 1.0388868876536621}",
      "hasCurveFrom": false,
      "hasCurveTo": true,
      "point": "{0.19642857142857142, 0.8905838700303752}"
    },
    {
      "_class": "curvePoint",
      "cornerRadius": 0,
      "curveFrom": "{0.21406250000000002, 0.14651623427842803}",
      "curveMode": 4,
      "curveTo": "{0.19642857142857142, 0.281546004197049}",
      "hasCurveFrom": true,
      "hasCurveTo": false,
      "point": "{0.19642857142857142, 0.281546004197049}"
    },
    {
      "_class": "curvePoint",
      "cornerRadius": 0,
      "curveFrom": "{0.39285714285714285, 0.29813756382788142}",
      "curveMode": 4,
      "curveTo": "{0.39285714285714285, 0.15289760336720976}",
      "hasCurveFrom": false,
      "hasCurveTo": true,
      "point": "{0.39285714285714285, 0.29813756382788142}"
    },
    {
      "_class": "curvePoint",
      "cornerRadius": 0,
      "curveFrom": "{0.39285714285714285, 0.89339167242943918}",
      "curveMode": 4,
      "curveTo": "{0.39285714285714285, 0.7455991643332549}",
      "hasCurveFrom": true,
      "hasCurveTo": false,
      "point": "{0.39285714285714285, 0.7455991643332549}"
    },
    {
      "_class": "curvePoint",
      "cornerRadius": 0,
      "curveFrom": "{0.6071428571428571, 0.7455991643332549}",
      "curveMode": 4,
      "curveTo": "{0.6071428571428571, 0.89364692719299055}",
      "hasCurveFrom": false,
      "hasCurveTo": true,
      "point": "{0.6071428571428571, 0.7455991643332549}"
    },
    {
      "_class": "curvePoint",
      "cornerRadius": 0,
      "curveFrom": "{0.61897321428571428, 0.30962402818768853}",
      "curveMode": 4,
      "curveTo": "{0.6071428571428571, 0.44924838385023225}",
      "hasCurveFrom": true,
      "hasCurveTo": false,
      "point": "{0.6071428571428571, 0.44924838385023225}"
    },
    {
      "_class": "curvePoint",
      "cornerRadius": 0,
      "curveFrom": "{0.8035714285714286, 0.46022433868293683}",
      "curveMode": 4,
      "curveTo": "{0.8035714285714286, 0.31523963298581642}",
      "hasCurveFrom": false,
      "hasCurveTo": true,
      "point": "{0.8035714285714286, 0.46022433868293683}"
    },
    {
      "_class": "curvePoint",
      "cornerRadius": 0,
      "curveFrom": "{0.8035714285714286, 0.67387257577534843}",
      "curveMode": 4,
      "curveTo": "{0.8035714285714286, 0.52097497240813873}",
      "hasCurveFrom": true,
      "hasCurveTo": false,
      "point": "{0.8035714285714286, 0.52097497240813873}"
    },
    {
      "_class": "curvePoint",
      "cornerRadius": 0,
      "curveFrom": "{1, 0.52097497240813873}",
      "curveMode": 4,
      "curveTo": "{1, 0.66544916857815661}",
      "hasCurveFrom": false,
      "hasCurveTo": true,
      "point": "{1, 0.52097497240813873}"
    },
    {
      "_class": "curvePoint",
      "cornerRadius": 0,
      "curveFrom": "{1, 0}",
      "curveMode": 1,
      "curveTo": "{1, 0}",
      "hasCurveFrom": false,
      "hasCurveTo": false,
      "point": "{1, 0}"
    }
  ],
  "resizingConstraint": 63,
  "resizingType": 0,
  "rotation": 0,
  "shouldBreakMaskChain": false,
  "style": {
    "_class": "style",
    "blur": {
      "_class": "blur",
      "center": "{0.5, 0.5}",
      "isEnabled": false,
      "motionAngle": 0,
      "radius": 10,
      "saturation": 1,
      "type": 0
    },
    "borderOptions": {
      "_class": "borderOptions",
      "dashPattern": [
      ],
      "isEnabled": true,
      "lineCapStyle": 0,
      "lineJoinStyle": 0
    },
    "borders": [
    ],
    "colorControls": {
      "_class": "colorControls",
      "brightness": 0,
      "contrast": 1,
      "hue": 0,
      "isEnabled": false,
      "saturation": 1
    },
    "contextSettings": {
      "_class": "graphicsContextSettings",
      "blendMode": 0,
      "opacity": 1
    },
    "do_objectID": "5579F407-E46B-44F8-BE40-FDFF896AED5D",
    "endMarkerType": 0,
    "fills": [
    ],
    "innerShadows": [
    ],
    "miterLimit": 10,
    "shadows": [
    ],
    "startMarkerType": 0,
    "windingRule": 1
  }
}