{
  "_class": "group",
  "do_objectID": "0B96DE7E-4044-4B41-BD13-B5E0E5AF6C23",
  "exportOptions": {
    "_class": "exportOptions",
    "exportFormats": [
    ],
    "includedLayerIds": [
    ],
    "layerOptions": 0,
    "shouldTrim": false
  },
  "frame": {
    "_class": "rect",
    "constrainProportions": false,
    "height": 12,
    "width": 16,
    "x": 0,
    "y": 0
  },
  "hasClickThrough": false,
  "isFlippedHorizontal": false,
  "isFlippedVertical": false,
  "isLocked": false,
  "isVisible": true,
  "layerListExpandedType": 0,
  "layers": [
    {
      "class": "shapeGroup",
      "id": "88EE92D6-7B3F-4679-8566-F17FD69F2C6D"
    },
    {
      "class": "shapeGroup",
      "id": "BD5E1D23-0249-4511-9633-706630CFD815"
    },
    {
      "class": "group",
      "id": "AEA8BE95-4FA7-4A7B-9BA1-73B38802AB65"
    },
    {
      "class": "symbolInstance",
      "id": "BEF62F8F-DB41-4507-9580-2AE6243F93B3"
    }
  ],
  "name": "Nova Scotia",
  "nameIsFixed": true,
  "resizingConstraint": 63,
  "resizingType": 0,
  "rotation": 0,
  "shouldBreakMaskChain": false,
  "style": {
    "_class": "style",
    "endDecorationType": 0,
    "miterLimit": 10,
    "startDecorationType": 0
  },
  "userInfo": {
    "com.animaapp.stc-sketch-plugin": {
      "kModelPropertiesKey": {
      }
    }
  }
}