{
  "_class": "group",
  "booleanOperation": 0,
  "clippingMaskMode": 0,
  "do_objectID": "8A227874-0958-47A6-985E-0887A19560F2",
  "exportOptions": {
    "_class": "exportOptions",
    "do_objectID": "3868A189-AAD4-4386-B74F-A08E895267B5",
    "exportFormats": [
    ],
    "includedLayerIds": [
    ],
    "layerOptions": 0,
    "shouldTrim": false
  },
  "frame": {
    "_class": "rect",
    "constrainProportions": false,
    "do_objectID": "CE450714-944F-4CA2-9640-276FC209405E",
    "height": 13,
    "width": 29,
    "x": 559,
    "y": 265
  },
  "groupLayout": {
    "_class": "MSImmutableFreeformGroupLayout",
    "do_objectID": "18B6F802-F8B1-4979-83E9-18664DF86046"
  },
  "hasClickThrough": false,
  "hasClippingMask": false,
  "isFixedToViewport": false,
  "isFlippedHorizontal": false,
  "isFlippedVertical": false,
  "isLocked": false,
  "isVisible": true,
  "layerListExpandedType": 2,
  "layers": [
    {
      "class": "text",
      "id": "E01C4770-4BE1-45EC-9258-D25884F52AF3"
    }
  ],
  "maintainScrollPosition": false,
  "name": "Group 2 Copy",
  "nameIsFixed": false,
  "resizingConstraint": 63,
  "resizingType": 0,
  "rotation": 0,
  "shouldBreakMaskChain": false,
  "style": {
    "_class": "style",
    "blur": {
      "_class": "blur",
      "center": "{0.5, 0.5}",
      "do_objectID": "BCD7372D-9A52-4FAB-AF33-9A51D3EFA4CC",
      "isEnabled": false,
      "motionAngle": 0,
      "radius": 7.199999380111706,
      "saturation": 1,
      "type": 0
    },
    "borderOptions": {
      "_class": "borderOptions",
      "dashPattern": [
      ],
      "do_objectID": "225F1329-6BA7-4DDA-9B29-B746C07BA4DD",
      "isEnabled": true,
      "lineCapStyle": 0,
      "lineJoinStyle": 0
    },
    "borders": [
    ],
    "colorControls": {
      "_class": "colorControls",
      "brightness": 0,
      "contrast": 1,
      "do_objectID": "5A2D64D3-859D-4007-B3D2-FC6685C77741",
      "hue": 0,
      "isEnabled": false,
      "saturation": 1
    },
    "contextSettings": {
      "_class": "graphicsContextSettings",
      "blendMode": 0,
      "do_objectID": "6076E013-A615-484D-89E0-E4A5671D0979",
      "opacity": 1
    },
    "do_objectID": "19F52AF5-5DCA-4812-BF74-77A3530D239F",
    "endMarkerType": 0,
    "fills": [
    ],
    "innerShadows": [
    ],
    "miterLimit": 10,
    "shadows": [
    ],
    "startMarkerType": 0,
    "windingRule": 1
  }
}