{
  "_class": "shapePath",
  "booleanOperation": -1,
  "clippingMaskMode": 0,
  "do_objectID": "0CA8DBC6-E1D5-47D8-BDF2-87F635536C50",
  "edited": true,
  "exportOptions": {
    "_class": "exportOptions",
    "exportFormats": [
    ],
    "includedLayerIds": [
    ],
    "layerOptions": 0,
    "shouldTrim": false
  },
  "frame": {
    "_class": "rect",
    "constrainProportions": false,
    "height": 5.491935483870968,
    "width": 4.559564516129033,
    "x": 9.205645161290322,
    "y": 9.238548387096774
  },
  "hasClippingMask": false,
  "isClosed": true,
  "isFixedToViewport": false,
  "isFlippedHorizontal": false,
  "isFlippedVertical": false,
  "isLocked": false,
  "isVisible": true,
  "layerListExpandedType": 0,
  "name": "Path",
  "nameIsFixed": false,
  "pointRadiusBehaviour": 1,
  "points": [
    {
      "_class": "curvePoint",
      "cornerRadius": 0,
      "curveFrom": "{0.14667147753923868, 1}",
      "curveMode": 3,
      "curveTo": "{0.64051108446265026, 1}",
      "hasCurveFrom": true,
      "hasCurveTo": true,
      "point": "{0.38278273604227903, 1}"
    },
    {
      "_class": "curvePoint",
      "cornerRadius": 0,
      "curveFrom": "{0, 0.24437004405286336}",
      "curveMode": 3,
      "curveTo": "{0, 0.86235242290748904}",
      "hasCurveFrom": true,
      "hasCurveTo": true,
      "point": "{0, 0.64078414096916292}"
    },
    {
      "_class": "curvePoint",
      "cornerRadius": 0,
      "curveFrom": "{0.85876197854209368, 0}",
      "curveMode": 3,
      "curveTo": "{0.32663348579554496, 0}",
      "hasCurveFrom": true,
      "hasCurveTo": true,
      "point": "{0.62219439462597237, 0}"
    },
    {
      "_class": "curvePoint",
      "cornerRadius": 0,
      "curveFrom": "{1, 0.75622026431718081}",
      "curveMode": 3,
      "curveTo": "{1, 0.13428193832599106}",
      "hasCurveFrom": true,
      "hasCurveTo": true,
      "point": "{1, 0.35920704845814988}"
    }
  ],
  "resizingConstraint": 63,
  "resizingType": 0,
  "rotation": 0,
  "shouldBreakMaskChain": false,
  "style": {
    "_class": "style",
    "blur": {
      "_class": "blur",
      "center": "{0.5, 0.5}",
      "isEnabled": false,
      "motionAngle": 0,
      "radius": 10,
      "saturation": 1,
      "type": 0
    },
    "borderOptions": {
      "_class": "borderOptions",
      "dashPattern": [
      ],
      "isEnabled": true,
      "lineCapStyle": 0,
      "lineJoinStyle": 0
    },
    "borders": [
    ],
    "colorControls": {
      "_class": "colorControls",
      "brightness": 0,
      "contrast": 1,
      "hue": 0,
      "isEnabled": false,
      "saturation": 1
    },
    "contextSettings": {
      "_class": "graphicsContextSettings",
      "blendMode": 0,
      "opacity": 1
    },
    "do_objectID": "413364E8-2484-4E45-9318-80A224AEA5B9",
    "endMarkerType": 0,
    "fills": [
    ],
    "innerShadows": [
    ],
    "miterLimit": 10,
    "shadows": [
    ],
    "startMarkerType": 0,
    "windingRule": 1
  }
}