{
  "_class": "group",
  "booleanOperation": -1,
  "clippingMaskMode": 0,
  "do_objectID": "F529287F-BE7F-42DD-9749-DC23139BFF2F",
  "exportOptions": {
    "_class": "exportOptions",
    "do_objectID": "20569AE6-103B-4A3E-A17C-E42CC314B307",
    "exportFormats": [
    ],
    "includedLayerIds": [
    ],
    "layerOptions": 0,
    "shouldTrim": false
  },
  "frame": {
    "_class": "rect",
    "constrainProportions": false,
    "do_objectID": "A80ECE0C-4B0E-4C8E-BEF8-79C5236954D4",
    "height": 35,
    "width": 546,
    "x": 0,
    "y": 26
  },
  "groupLayout": {
    "_class": "MSImmutableFreeformGroupLayout",
    "do_objectID": "BB0498CD-37CB-49BC-8400-4E42EE119F66"
  },
  "hasClickThrough": false,
  "hasClippingMask": false,
  "isFixedToViewport": false,
  "isFlippedHorizontal": false,
  "isFlippedVertical": false,
  "isLocked": false,
  "isVisible": true,
  "layerListExpandedType": 2,
  "layers": [
    {
      "class": "rectangle",
      "id": "0A15121E-8E65-472A-AD99-C578F638530D"
    },
    {
      "class": "text",
      "id": "335C6344-A9C0-4692-9196-1C78DD7222A7"
    }
  ],
  "name": "Group 4",
  "nameIsFixed": false,
  "resizingConstraint": 63,
  "resizingType": 0,
  "rotation": 0,
  "shouldBreakMaskChain": false,
  "style": {
    "_class": "style",
    "do_objectID": "157B40E8-2C37-473F-BDAC-167F26918487",
    "endMarkerType": 0,
    "miterLimit": 10,
    "startMarkerType": 0,
    "windingRule": 1
  }
}