{
  "_class": "group",
  "booleanOperation": 0,
  "clippingMaskMode": 0,
  "do_objectID": "AC1E3728-FD91-4FFA-9446-1D824D43BDC4",
  "exportOptions": {
    "_class": "exportOptions",
    "do_objectID": "4F5C0E75-7F70-4746-8149-B75A20C6A64A",
    "exportFormats": [
    ],
    "includedLayerIds": [
    ],
    "layerOptions": 0,
    "shouldTrim": false
  },
  "frame": {
    "_class": "rect",
    "constrainProportions": false,
    "do_objectID": "B35BD8BE-62F7-4816-B4E0-D83B8972C129",
    "height": 22,
    "width": 235,
    "x": 17,
    "y": 51
  },
  "groupLayout": {
    "_class": "MSImmutableFreeformGroupLayout"
  },
  "hasClickThrough": false,
  "hasClippingMask": false,
  "isFixedToViewport": false,
  "isFlippedHorizontal": false,
  "isFlippedVertical": false,
  "isLocked": false,
  "isVisible": true,
  "layerListExpandedType": 0,
  "layers": [
    {
      "class": "rectangle",
      "id": "4BC5A6C1-C756-4C68-85C1-B3657F6578C3"
    },
    {
      "class": "text",
      "id": "40ECCD40-55B1-417D-9A53-5C5BFB8895CC"
    },
    {
      "class": "text",
      "id": "C2F5577A-CAAB-4ECC-9229-748952B69472"
    }
  ],
  "name": "Group 3 Copy 2",
  "nameIsFixed": false,
  "resizingConstraint": 63,
  "resizingType": 0,
  "rotation": 0,
  "shouldBreakMaskChain": false,
  "style": {
    "_class": "style",
    "contextSettings": {
      "_class": "graphicsContextSettings",
      "blendMode": 0,
      "do_objectID": "8DD8D749-35D9-4030-9795-71B37CDF948F",
      "opacity": 0.5199999809265137
    },
    "do_objectID": "12F79D89-5121-4F64-A7AD-407237B1D440",
    "endMarkerType": 0,
    "miterLimit": 10,
    "startMarkerType": 0,
    "windingRule": 1
  }
}