{
  "_class": "group",
  "booleanOperation": -1,
  "clippingMaskMode": 0,
  "do_objectID": "E7BB244A-3077-4347-A22B-C77367D71F51",
  "exportOptions": {
    "_class": "exportOptions",
    "do_objectID": "C9CF4EDE-6D4D-46CC-9D8D-8885661193DD",
    "exportFormats": [
    ],
    "includedLayerIds": [
    ],
    "layerOptions": 0,
    "shouldTrim": false
  },
  "frame": {
    "_class": "rect",
    "constrainProportions": false,
    "do_objectID": "649D6D85-EACA-44F1-9DF2-90F8D56B94D0",
    "height": 22,
    "width": 22,
    "x": 902,
    "y": 169
  },
  "groupLayout": {
    "_class": "MSImmutableFreeformGroupLayout",
    "do_objectID": "C7B6CEC0-58BE-4FD3-896F-8A277C512126"
  },
  "hasClickThrough": false,
  "hasClippingMask": false,
  "isFixedToViewport": false,
  "isFlippedHorizontal": false,
  "isFlippedVertical": false,
  "isLocked": false,
  "isVisible": true,
  "layerListExpandedType": 0,
  "layers": [
    {
      "class": "group",
      "id": "AF6E0688-502D-4BFB-8C78-3433713178C1"
    },
    {
      "class": "text",
      "id": "C125675A-13DD-482F-A428-58E5E500DEF3"
    }
  ],
  "maintainScrollPosition": false,
  "name": "SaveIconDash Copy 2",
  "nameIsFixed": false,
  "resizingConstraint": 63,
  "resizingType": 0,
  "rotation": 0,
  "shouldBreakMaskChain": false,
  "style": {
    "_class": "style",
    "blur": {
      "_class": "blur",
      "center": "{0.5, 0.5}",
      "do_objectID": "0766CDC0-D9B5-4AB4-B023-BADB34672094",
      "isEnabled": false,
      "motionAngle": 0,
      "radius": 9.899999952316278,
      "saturation": 1,
      "type": 0
    },
    "borderOptions": {
      "_class": "borderOptions",
      "dashPattern": [
      ],
      "do_objectID": "4C8093A2-5710-4F86-8696-5B70AAEB2BA4",
      "isEnabled": true,
      "lineCapStyle": 0,
      "lineJoinStyle": 0
    },
    "borders": [
    ],
    "colorControls": {
      "_class": "colorControls",
      "brightness": 0,
      "contrast": 1,
      "do_objectID": "5C5FE72E-2B12-4D50-B67A-BD5ACFEDB83F",
      "hue": 0,
      "isEnabled": false,
      "saturation": 1
    },
    "contextSettings": {
      "_class": "graphicsContextSettings",
      "blendMode": 0,
      "do_objectID": "229D32A1-624B-406C-B726-AED6F0BD59E7",
      "opacity": 1
    },
    "do_objectID": "34097127-5E1E-4C9A-B9D6-1B998F5323F0",
    "endMarkerType": 0,
    "fills": [
    ],
    "innerShadows": [
    ],
    "miterLimit": 10,
    "shadows": [
    ],
    "startMarkerType": 0,
    "windingRule": 1
  }
}