{
  "_class": "group",
  "booleanOperation": 0,
  "clippingMaskMode": 0,
  "do_objectID": "60E798C6-4A42-4312-B836-882F5F2F916B",
  "exportOptions": {
    "_class": "exportOptions",
    "do_objectID": "17977478-A811-45B4-B545-D30866D91BB9",
    "exportFormats": [
    ],
    "includedLayerIds": [
    ],
    "layerOptions": 0,
    "shouldTrim": false
  },
  "frame": {
    "_class": "rect",
    "constrainProportions": false,
    "do_objectID": "DCC56986-33CD-4012-9D20-481058DFB66C",
    "height": 22,
    "width": 238,
    "x": 282,
    "y": 51
  },
  "groupLayout": {
    "_class": "MSImmutableFreeformGroupLayout"
  },
  "hasClickThrough": false,
  "hasClippingMask": false,
  "isFixedToViewport": false,
  "isFlippedHorizontal": false,
  "isFlippedVertical": false,
  "isLocked": false,
  "isVisible": true,
  "layerListExpandedType": 0,
  "layers": [
    {
      "class": "rectangle",
      "id": "64F9019B-6021-4116-8812-0CB867FF0C5C"
    },
    {
      "class": "text",
      "id": "C2C7002C-366F-41AF-BA82-DE53321D6269"
    },
    {
      "class": "text",
      "id": "C3B5DF1C-427A-4260-9797-466ABB9E55F2"
    }
  ],
  "name": "Group 3 Copy 3",
  "nameIsFixed": false,
  "resizingConstraint": 63,
  "resizingType": 0,
  "rotation": 0,
  "shouldBreakMaskChain": false,
  "style": {
    "_class": "style",
    "do_objectID": "EFDF8AB0-F14E-43DE-875A-3A8DE8C7D395",
    "endMarkerType": 0,
    "miterLimit": 10,
    "startMarkerType": 0,
    "windingRule": 1
  }
}