{
  "_class": "group",
  "do_objectID": "C998FE98-8D93-4C7B-BE5D-CBA724B5A001",
  "exportOptions": {
    "_class": "exportOptions",
    "exportFormats": [
    ],
    "includedLayerIds": [
    ],
    "layerOptions": 0,
    "shouldTrim": false
  },
  "frame": {
    "_class": "rect",
    "constrainProportions": false,
    "height": 12,
    "width": 16,
    "x": 0,
    "y": 0
  },
  "hasClickThrough": false,
  "isFlippedHorizontal": false,
  "isFlippedVertical": false,
  "isLocked": false,
  "isVisible": true,
  "layerListExpandedType": 0,
  "layers": [
    {
      "class": "shapeGroup",
      "id": "25084D82-89FB-4F10-88D2-DE61E0C48B8D"
    },
    {
      "class": "shapeGroup",
      "id": "0596A490-14C9-457E-B06B-B0664EB68E57"
    },
    {
      "class": "shapeGroup",
      "id": "B10DD750-2EFF-4879-B7BE-6666CAC61DE3"
    },
    {
      "class": "shapeGroup",
      "id": "62200B91-8728-4B1E-9A47-50106BA76312"
    },
    {
      "class": "shapeGroup",
      "id": "71D91034-B02C-4768-813A-BB67BE69F943"
    },
    {
      "class": "shapeGroup",
      "id": "E8838148-07F3-4957-AE58-6175603FEBBC"
    },
    {
      "class": "shapeGroup",
      "id": "7841B212-8B11-4571-8847-0815D2FA144B"
    },
    {
      "class": "symbolInstance",
      "id": "99C48373-8DDA-4B1E-9803-FA18EAC89BA9"
    }
  ],
  "name": "Martinique",
  "nameIsFixed": true,
  "resizingConstraint": 63,
  "resizingType": 0,
  "rotation": 0,
  "shouldBreakMaskChain": false,
  "style": {
    "_class": "style",
    "endDecorationType": 0,
    "miterLimit": 10,
    "startDecorationType": 0
  },
  "userInfo": {
    "com.animaapp.stc-sketch-plugin": {
      "kModelPropertiesKey": {
      }
    }
  }
}