{
  "_class": "shapePath",
  "booleanOperation": -1,
  "clippingMaskMode": 0,
  "do_objectID": "8E9E654A-ADFD-4F6C-ABFB-AB9D066A208E",
  "edited": true,
  "exportOptions": {
    "_class": "exportOptions",
    "do_objectID": "84D7913D-1FA3-4F8B-8FE5-FC371C536F5F",
    "exportFormats": [
    ],
    "includedLayerIds": [
    ],
    "layerOptions": 0,
    "shouldTrim": false
  },
  "frame": {
    "_class": "rect",
    "constrainProportions": false,
    "do_objectID": "4D7E1521-B1CC-4A84-8D21-08CD9B775D97",
    "height": 5.923076923076925,
    "width": 5.923076923076925,
    "x": 1.692307692307692,
    "y": 1.692307692307692
  },
  "hasClippingMask": false,
  "isClosed": true,
  "isFixedToViewport": false,
  "isFlippedHorizontal": false,
  "isFlippedVertical": false,
  "isLocked": false,
  "isVisible": true,
  "layerListExpandedType": 0,
  "name": "Path",
  "nameIsFixed": false,
  "pointRadiusBehaviour": 0,
  "points": [
    {
      "_class": "curvePoint",
      "cornerRadius": 0,
      "curveFrom": "{1, 0.7756696428571429}",
      "curveMode": 4,
      "curveTo": "{1, 0.5}",
      "hasCurveFrom": true,
      "hasCurveTo": false,
      "point": "{1, 0.5}"
    },
    {
      "_class": "curvePoint",
      "cornerRadius": 0,
      "curveFrom": "{0.22433035714285715, 1}",
      "curveMode": 2,
      "curveTo": "{0.7756696428571429, 1}",
      "hasCurveFrom": true,
      "hasCurveTo": true,
      "point": "{0.5, 1}"
    },
    {
      "_class": "curvePoint",
      "cornerRadius": 0,
      "curveFrom": "{0, 0.22433035714285715}",
      "curveMode": 2,
      "curveTo": "{0, 0.7756696428571429}",
      "hasCurveFrom": true,
      "hasCurveTo": true,
      "point": "{0, 0.5}"
    },
    {
      "_class": "curvePoint",
      "cornerRadius": 0,
      "curveFrom": "{0.7756696428571429, 0}",
      "curveMode": 2,
      "curveTo": "{0.22433035714285715, 0}",
      "hasCurveFrom": true,
      "hasCurveTo": true,
      "point": "{0.5, 0}"
    },
    {
      "_class": "curvePoint",
      "cornerRadius": 0,
      "curveFrom": "{1, 0.5}",
      "curveMode": 4,
      "curveTo": "{1, 0.22433035714285715}",
      "hasCurveFrom": false,
      "hasCurveTo": true,
      "point": "{1, 0.5}"
    }
  ],
  "resizingConstraint": 63,
  "resizingType": 0,
  "rotation": 0,
  "shouldBreakMaskChain": false,
  "style": {
    "_class": "style",
    "blur": {
      "_class": "blur",
      "center": "{0.5, 0.5}",
      "do_objectID": "B880E33C-8497-4C15-8ED9-7161C267882A",
      "isEnabled": false,
      "motionAngle": 0,
      "radius": 8.799999666213978,
      "saturation": 1,
      "type": 0
    },
    "contextSettings": {
      "_class": "graphicsContextSettings",
      "blendMode": 0,
      "do_objectID": "3A745F36-EFDE-4D0A-BCD8-D87CC893C556",
      "opacity": 0.4500000178813934
    },
    "do_objectID": "F820C776-9BBC-42F9-A0C6-D3A9DA73FF3E",
    "endMarkerType": 0,
    "fills": [
      {
        "_class": "fill",
        "color": {
          "_class": "color",
          "alpha": 1,
          "blue": 0.5708607385504707,
          "green": 0.5708607385504707,
          "red": 0.5748299319727891
        },
        "fillType": 0,
        "isEnabled": true,
        "noiseIndex": 0,
        "noiseIntensity": 0,
        "patternFillType": 0,
        "patternTileScale": 1
      }
    ],
    "miterLimit": 10,
    "startMarkerType": 0,
    "textStyle": {
      "_class": "textStyle",
      "do_objectID": "B011C3C4-A980-4231-860D-7A78F5B37064",
      "encodedAttributes": {
        "MSAttributedStringColorAttribute": {
          "_class": "color",
          "alpha": 1,
          "blue": 0.8274509804,
          "green": 0.8235294118,
          "red": 0.8156862745
        },
        "MSAttributedStringFontAttribute": {
          "_class": "fontDescriptor",
          "attributes": {
            "NSCTFontUIUsageAttribute": "CTFontRegularUsage",
            "size": 14
          }
        },
        "paragraphStyle": {
          "_class": "paragraphStyle",
          "allowsDefaultTighteningForTruncation": 0,
          "baseWritingDirection": 0,
          "minimumLineHeight": 14,
          "tabStops": [
          ]
        }
      },
      "verticalAlignment": 0
    },
    "windingRule": 1
  }
}