{
  "_class": "symbolInstance",
  "booleanOperation": -1,
  "clippingMaskMode": 0,
  "do_objectID": "F1564D97-068D-479A-B500-C713401D291F",
  "exportOptions": {
    "_class": "exportOptions",
    "do_objectID": "F2CEF2C6-CE0B-41B1-82C9-322EE81E676C",
    "exportFormats": [
    ],
    "includedLayerIds": [
    ],
    "layerOptions": 0,
    "shouldTrim": false
  },
  "frame": {
    "_class": "rect",
    "constrainProportions": false,
    "do_objectID": "9AF862BD-82CE-4B46-9A04-BD103BEA59C0",
    "height": 24,
    "width": 24,
    "x": 629,
    "y": 315
  },
  "hasClippingMask": false,
  "horizontalSpacing": 0,
  "isFixedToViewport": false,
  "isFlippedHorizontal": false,
  "isFlippedVertical": false,
  "isLocked": false,
  "isVisible": true,
  "layerListExpandedType": 0,
  "maintainScrollPosition": false,
  "name": "ic_expand_more copy",
  "nameIsFixed": false,
  "overrideValues": [
    {
      "_class": "overrideValue",
      "do_objectID": "2316794A-2D17-499A-A5E9-0F34B8ACCB13",
      "overrideName": "C088DFEF-AE35-40A2-8130-83A4D480AF1C_symbolID",
      "value": "4E9C0AB1-9961-472A-8E53-D8EA5B479EC1"
    }
  ],
  "resizingConstraint": 63,
  "resizingType": 0,
  "rotation": 0,
  "scale": 1,
  "shouldBreakMaskChain": false,
  "style": {
    "_class": "style",
    "blur": {
      "_class": "blur",
      "center": "{0.5, 0.5}",
      "do_objectID": "E6C32023-8039-4269-9844-4129C7A62F20",
      "isEnabled": false,
      "motionAngle": 0,
      "radius": 10,
      "saturation": 1,
      "type": 0
    },
    "borderOptions": {
      "_class": "borderOptions",
      "dashPattern": [
      ],
      "do_objectID": "6EDCAF3A-DE8A-4C8C-BD11-5B5CEC310474",
      "isEnabled": true,
      "lineCapStyle": 0,
      "lineJoinStyle": 0
    },
    "borders": [
    ],
    "colorControls": {
      "_class": "colorControls",
      "brightness": 0,
      "contrast": 1,
      "do_objectID": "5A9CA4F3-FC16-45CB-8630-7FADFBCF8E1E",
      "hue": 0,
      "isEnabled": true,
      "saturation": 1
    },
    "contextSettings": {
      "_class": "graphicsContextSettings",
      "blendMode": 0,
      "do_objectID": "15E086DE-E323-4AFF-B463-B0D4A3DE35A2",
      "opacity": 1
    },
    "do_objectID": "5D4A96B3-F90B-4F63-9E7C-D3C3C647375F",
    "endMarkerType": 0,
    "fills": [
    ],
    "innerShadows": [
    ],
    "miterLimit": 10,
    "shadows": [
    ],
    "startMarkerType": 0,
    "windingRule": 1
  },
  "symbolID": "3644D4DB-F41B-4110-95D1-292B3C9C90B0",
  "verticalSpacing": 0
}