{
  "_class": "group",
  "do_objectID": "0E1FB1D4-D6A4-44A8-9A64-FB498F8D4F20",
  "exportOptions": {
    "_class": "exportOptions",
    "exportFormats": [
    ],
    "includedLayerIds": [
    ],
    "layerOptions": 0,
    "shouldTrim": false
  },
  "frame": {
    "_class": "rect",
    "constrainProportions": false,
    "height": 12,
    "width": 16,
    "x": 0,
    "y": 0
  },
  "hasClickThrough": false,
  "isFlippedHorizontal": false,
  "isFlippedVertical": false,
  "isLocked": false,
  "isVisible": true,
  "layerListExpandedType": 0,
  "layers": [
    {
      "class": "shapeGroup",
      "id": "C9430032-B1BF-4377-93B8-8B1CF1C940D1"
    },
    {
      "class": "shapeGroup",
      "id": "06023DC1-28E3-4C83-90DC-50ADA23C4BD6"
    },
    {
      "class": "shapeGroup",
      "id": "31C2DCEF-B975-490B-A928-147503C210FD"
    },
    {
      "class": "shapeGroup",
      "id": "946856F7-FA1B-4350-A659-5494D31E3388"
    },
    {
      "class": "symbolInstance",
      "id": "DD7707F4-59A5-4FF8-80DC-36546E7FE0BF"
    }
  ],
  "name": "Russia",
  "nameIsFixed": true,
  "resizingConstraint": 63,
  "resizingType": 0,
  "rotation": 0,
  "shouldBreakMaskChain": false,
  "style": {
    "_class": "style",
    "endDecorationType": 0,
    "miterLimit": 10,
    "startDecorationType": 0
  },
  "userInfo": {
    "com.animaapp.stc-sketch-plugin": {
      "kModelPropertiesKey": {
      }
    }
  }
}